gymboy-0.0.1.dist-info/METADATA
gymboy-0.0.1.dist-info/WHEEL
gymboy-0.0.1.dist-info/entry_points.txt
gymboy-0.0.1.dist-info/licenses/LICENSE
gymboy/__init__.py
gymboy/environments/__init__.py
gymboy/environments/env.py
gymboy/environments/kirby/__init__.py
gymboy/environments/kirby/dream_land_1/__init__.py
gymboy/environments/kirby/dream_land_1/_constant.py
gymboy/environments/kirby/dream_land_1/_memory.py
gymboy/environments/kirby/dream_land_1/kirby_dream_land_1.py
gymboy/environments/mario/__init__.py
gymboy/environments/mario/land_1/__init__.py
gymboy/environments/mario/land_1/_constant.py
gymboy/environments/mario/land_1/_memory.py
gymboy/environments/mario/land_1/super_mario_land_1.py
gymboy/environments/pokemon/__init__.py
gymboy/environments/pokemon/gen_1/__init__.py
gymboy/environments/pokemon/gen_1/_constant.py
gymboy/environments/pokemon/gen_1/_memory.py
gymboy/environments/pokemon/gen_1/blue.py
gymboy/environments/pokemon/gen_1/red.py
gymboy/environments/pokemon/gen_1/yellow.py
gymboy/environments/pokemon/gen_2/__init__.py
gymboy/environments/pokemon/gen_2/_constant.py
gymboy/environments/pokemon/gen_2/_memory.py
gymboy/environments/pokemon/gen_2/gold.py
gymboy/environments/pokemon/gen_2/silver.py
gymboy/environments/tetris/__init__.py
gymboy/environments/tetris/tetris/__init__.py
gymboy/environments/tetris/tetris/_constant.py
gymboy/environments/tetris/tetris/_memory.py
gymboy/environments/tetris/tetris/tetris.py
gymboy/registration.py
gymboy/utils/__init__.py
gymboy/utils/binary.py
gymboy-0.0.1.dist-info/RECORD
