Metadata-Version: 2.1
Name: gymboy
Version: 0.0.1
Summary: Gameboy (Color) environments in Gymnasium 🤖
Author: Dennis Jabs
License: MIT License
Project-URL: Homepage, https://github.com/nobodyPerfecZ/gymboy
Project-URL: Issues, https://github.com/nobodyPerfecZ/gymboy/issues
Requires-Python: >=3.10
Requires-Dist: gymnasium>=1.1.1
Requires-Dist: pyboy>=2.5.3
Requires-Dist: scikit-image>=0.25.2
